setup.py
common/__init__.py
common/decos.py
common/descryptors.py
common/errors.py
common/metaclasses.py
common/utils.py
common/variables.py
logs/__init__.py
logs/config_client_log.py
logs/config_server_log.py
mess_server_october17.10.2021.egg-info/PKG-INFO
mess_server_october17.10.2021.egg-info/SOURCES.txt
mess_server_october17.10.2021.egg-info/dependency_links.txt
mess_server_october17.10.2021.egg-info/requires.txt
mess_server_october17.10.2021.egg-info/top_level.txt
server/__init__.py
server/add_user.py
server/config_window.py
server/core.py
server/database.py
server/main_window.py
server/remove_user.py
server/stat_window.py
unit_tests/__init__.py