Metadata-Version: 2.1
Name: mess-server-october17.10.2021
Version: 0.0.1
Summary: mess_server_projoctober
Home-page: UNKNOWN
Author: Andrey Yanke
Author-email: ayanke@bk.ru
License: UNKNOWN
Platform: UNKNOWN
